fds/__init__.py
fds/sdk/__init__.py
fds/sdk/Cabot/__init__.py
fds/sdk/Cabot/api_client.py
fds/sdk/Cabot/configuration.py
fds/sdk/Cabot/exceptions.py
fds/sdk/Cabot/model_utils.py
fds/sdk/Cabot/rest.py
fds/sdk/Cabot/api/__init__.py
fds/sdk/Cabot/api/buying_models_api.py
fds/sdk/Cabot/api/classifications_api.py
fds/sdk/Cabot/api/overview_models_api.py
fds/sdk/Cabot/api/selling_models_api.py
fds/sdk/Cabot/api/sizing_models_api.py
fds/sdk/Cabot/apis/__init__.py
fds/sdk/Cabot/model/__init__.py
fds/sdk/Cabot/model/add_trim_holdings.py
fds/sdk/Cabot/model/add_trim_model_analytics.py
fds/sdk/Cabot/model/add_trim_request_body.py
fds/sdk/Cabot/model/add_trim_request_body_root.py
fds/sdk/Cabot/model/add_trim_response_options.py
fds/sdk/Cabot/model/add_trim_response_root.py
fds/sdk/Cabot/model/attributes.py
fds/sdk/Cabot/model/buy_context_model_analytics.py
fds/sdk/Cabot/model/buy_context_model_analytics_context.py
fds/sdk/Cabot/model/buy_context_model_analytics_context_attribute.py
fds/sdk/Cabot/model/buy_context_model_analytics_item.py
fds/sdk/Cabot/model/buy_context_model_analytics_item_range.py
fds/sdk/Cabot/model/buy_context_request_body.py
fds/sdk/Cabot/model/buy_context_request_body_root.py
fds/sdk/Cabot/model/buy_context_response_options.py
fds/sdk/Cabot/model/buy_context_response_root.py
fds/sdk/Cabot/model/buy_timing_holdings.py
fds/sdk/Cabot/model/buy_timing_model_analytics.py
fds/sdk/Cabot/model/buy_timing_request_body.py
fds/sdk/Cabot/model/buy_timing_request_body_root.py
fds/sdk/Cabot/model/buy_timing_response_options.py
fds/sdk/Cabot/model/buy_timing_response_root.py
fds/sdk/Cabot/model/classifications.py
fds/sdk/Cabot/model/classifications_response_options.py
fds/sdk/Cabot/model/classifications_response_root.py
fds/sdk/Cabot/model/client_error_response.py
fds/sdk/Cabot/model/construction_model_analytics.py
fds/sdk/Cabot/model/construction_model_analytics_active_weights.py
fds/sdk/Cabot/model/construction_model_analytics_active_weights_max_over.py
fds.sdk.Cabot-0.12.0.dist-info/LICENSE
fds.sdk.Cabot-0.12.0.dist-info/METADATA
fds.sdk.Cabot-0.12.0.dist-info/WHEEL
fds.sdk.Cabot-0.12.0.dist-info/top_level.txt
fds.sdk.Cabot-0.12.0.dist-info/RECORD
